finbourne_candela/__init__.py
finbourne_candela/api/__init__.py
finbourne_candela/api/apps_api.py
finbourne_candela/api/circuits_api.py
finbourne_candela/api/directives_api.py
finbourne_candela/api/models_api.py
finbourne_candela/api/sessions_api.py
finbourne_candela/api/system_api.py
finbourne_candela/api/tool_modules_api.py
finbourne_candela/api/traces_api.py
finbourne_candela/api/user_slots_api.py
finbourne_candela/api_client.py
finbourne_candela/api_response.py
finbourne_candela/configuration.py
finbourne_candela/exceptions.py
finbourne_candela/extensions/__init__.py
finbourne_candela/extensions/api_client.py
finbourne_candela/extensions/api_client_factory.py
finbourne_candela/extensions/api_configuration.py
finbourne_candela/extensions/configuration_loaders.py
finbourne_candela/extensions/configuration_options.py
finbourne_candela/extensions/file_access_token.py
finbourne_candela/extensions/proxy_config.py
finbourne_candela/extensions/refreshing_token.py
finbourne_candela/extensions/rest.py
finbourne_candela/extensions/retry.py
finbourne_candela/extensions/socket_keep_alive.py
finbourne_candela/extensions/tcp_keep_alive_connector.py
finbourne_candela/models/__init__.py
finbourne_candela/models/app_spec.py
finbourne_candela/models/base_tool.py
finbourne_candela/models/circuit_dto.py
finbourne_candela/models/confirm_dto.py
finbourne_candela/models/dev_session_start_request.py
finbourne_candela/models/directive.py
finbourne_candela/models/dto_arr.py
finbourne_candela/models/dto_bool.py
finbourne_candela/models/dto_const.py
finbourne_candela/models/dto_dict.py
finbourne_candela/models/dto_enum.py
finbourne_candela/models/dto_int.py
finbourne_candela/models/dto_obj.py
finbourne_candela/models/dto_real.py
finbourne_candela/models/dto_str.py
finbourne_candela/models/event.py
finbourne_candela/models/fields.py
finbourne_candela/models/http_validation_error.py
finbourne_candela/models/insert_context_dto.py
finbourne_candela/models/intent_dto.py
finbourne_candela_sdk-0.1.173.dist-info/METADATA
finbourne_candela_sdk-0.1.173.dist-info/WHEEL
finbourne_candela_sdk-0.1.173.dist-info/RECORD
