Metadata-Version: 2.1
Name: finbourne-candela-sdk
Version: 0.1.173
Summary: FINBOURNE Candela Platform Web API
Home-page: https://github.com/finbourne/candela-sdk-python
License: MIT
Keywords: OpenAPI,OpenAPI-Generator,FINBOURNE Candela Platform Web API,finbourne-candela-sdk
Author: OpenAPI Generator Community
Author-email: team@openapitools.org
Requires-Python: >=3.8,<4.0
Classifier: License :: OSI Approved :: MIT License
Classifier: Programming Language :: Python :: 3
Classifier: Programming Language :: Python :: 3.8
Classifier: Programming Language :: Python :: 3.9
Classifier: Programming Language :: Python :: 3.10
Classifier: Programming Language :: Python :: 3.11
Classifier: Programming Language :: Python :: 3.12
Classifier: Programming Language :: Python :: 3.13
Requires-Dist: aenum (>=3.1.11,<4.0.0)
Requires-Dist: aiohttp (>=3.8.4,<4.0.0)
Requires-Dist: pydantic (>=2.6.3,<3.0.0)
Requires-Dist: python-dateutil (>=2.8.2,<3.0.0)
Requires-Dist: requests (>=2,<3)
Requires-Dist: urllib3 (>=1.25.3,<2.0.0)
Project-URL: Repository, https://github.com/finbourne/candela-sdk-python
